flexfiles/__init__.py
flexfiles/filehandler.py
flexfiles-1.0.0rc1.dist-info/LICENSE
flexfiles-1.0.0rc1.dist-info/METADATA
flexfiles-1.0.0rc1.dist-info/WHEEL
flexfiles-1.0.0rc1.dist-info/top_level.txt
flexfiles-1.0.0rc1.dist-info/RECORD
